{"annotations": [{"completed_by": {"username": "massimiliano96", "first_name": "massimiliano96", "last_name": "", "avatar": "https://dagshub.com/avatars/16328"}, "result": [{"id": "caQ_8yREBV", "type": "rectanglelabels", "score": 0.9840280413627625, "value": {"x": 7.846244812011719, "y": 8.939521789550781, "width": 73.47108459472656, "height": 88.69557189941406, "rotation": 0, "rectanglelabels": ["E"]}, "origin": "prediction", "to_name": "image", "from_name": "label", "image_rotation": 0, "original_width": 200, "original_height": 200}], "was_cancelled": false, "ground_truth": false, "created_at": "2024-01-08T12:55:55.452443Z", "updated_at": "2024-01-08T12:55:55.452447Z", "lead_time": 1.084, "prediction": {"id": 3671, "task": 96861, "score": null, "result": [{"type": "rectanglelabels", "score": 0.9840280413627625, "value": {"x": 7.846244812011719, "y": 8.939521789550781, "width": 73.47108459472656, "height": 88.69557189941406, "rectanglelabels": ["E"]}, "to_name": "image", "from_name": "label"}], "cluster": null, "neighbors": null, "created_at": "2024-01-06T10:29:37.909132Z", "updated_at": "2024-01-06T10:29:37.909164Z", "created_ago": "2\u00a0days, 2\u00a0hours", "mislabeling": 0.0, "model_version": "4"}, "result_count": 0, "parent_prediction": 3671, "parent_annotation": null}], "drafts": [], "predictions": [3671], "data": {"image": "repo://1f7b73bdedcba73296b429e0036c55fcc4df7a4b/data_first_draft/E226.jpg"}, "meta": {}}