{"annotations": [{"completed_by": {"username": "massimiliano96", "first_name": "massimiliano96", "last_name": "", "avatar": "https://dagshub.com/avatars/16328"}, "result": [{"id": "3WBtKBb52z", "type": "rectanglelabels", "score": 0.7470149993896484, "value": {"x": 32.99954795837402, "y": 14.574508666992188, "width": 44.8243293762207, "height": 83.53385925292969, "rotation": 0, "rectanglelabels": ["K"]}, "origin": "prediction", "to_name": "image", "from_name": "label", "image_rotation": 0, "original_width": 200, "original_height": 200}], "was_cancelled": false, "ground_truth": false, "created_at": "2024-01-15T08:31:32.976537Z", "updated_at": "2024-01-15T08:31:32.976541Z", "lead_time": 2.309, "prediction": {"id": 4608, "task": 97646, "score": null, "result": [{"type": "rectanglelabels", "score": 0.7470149993896484, "value": {"x": 32.99954795837402, "y": 14.574508666992188, "width": 44.8243293762207, "height": 83.53385925292969, "rectanglelabels": ["K"]}, "to_name": "image", "from_name": "label"}], "cluster": null, "neighbors": null, "created_at": "2024-01-06T10:42:21.670255Z", "updated_at": "2024-01-06T10:42:21.670287Z", "created_ago": "1\u00a0week, 1\u00a0day", "mislabeling": 0.0, "model_version": "4"}, "result_count": 0, "parent_prediction": 4608, "parent_annotation": null}], "drafts": [], "predictions": [4608], "data": {"image": "repo://1f7b73bdedcba73296b429e0036c55fcc4df7a4b/data_first_draft/K981.jpg"}, "meta": {}}