{"annotations": [{"completed_by": {"username": "massimiliano96", "first_name": "massimiliano96", "last_name": "", "avatar": "https://dagshub.com/avatars/16328"}, "result": [{"id": "zV972GPkw2", "type": "rectanglelabels", "score": 0.9213898777961731, "value": {"x": 18.696861267089844, "y": 23.311927795410156, "width": 69.19197845458984, "height": 51.47589111328125, "rotation": 0, "rectanglelabels": ["C"]}, "origin": "prediction", "to_name": "image", "from_name": "label", "image_rotation": 0, "original_width": 200, "original_height": 200}], "was_cancelled": false, "ground_truth": false, "created_at": "2024-01-06T10:50:48.651868Z", "updated_at": "2024-01-06T10:50:48.651873Z", "lead_time": 2.012, "prediction": {"id": 3425, "task": 96647, "score": null, "result": [{"type": "rectanglelabels", "score": 0.9213898777961731, "value": {"x": 18.696861267089844, "y": 23.311927795410156, "width": 69.19197845458984, "height": 51.47589111328125, "rectanglelabels": ["C"]}, "to_name": "image", "from_name": "label"}], "cluster": null, "neighbors": null, "created_at": "2024-01-06T10:26:11.566465Z", "updated_at": "2024-01-06T10:26:11.566495Z", "created_ago": "24\u00a0minutes", "mislabeling": 0.0, "model_version": "4"}, "result_count": 0, "parent_prediction": 3425, "parent_annotation": null}], "drafts": [], "predictions": [3425, 5222], "data": {"image": "repo://1f7b73bdedcba73296b429e0036c55fcc4df7a4b/data_first_draft/C2782.jpg"}, "meta": {}}