{"annotations": [{"completed_by": {"username": "massimiliano96", "first_name": "massimiliano96", "last_name": "", "avatar": "https://dagshub.com/avatars/16328"}, "result": [{"id": "XRosgjp0La", "type": "rectanglelabels", "score": 0.8264628648757935, "value": {"x": 7.033531188964844, "y": 3.3487396240234375, "width": 64.20580291748047, "height": 69.46102142333984, "rotation": 0, "rectanglelabels": ["L"]}, "origin": "prediction", "to_name": "image", "from_name": "label", "image_rotation": 0, "original_width": 200, "original_height": 200}], "was_cancelled": false, "ground_truth": false, "created_at": "2024-01-15T08:38:30.473900Z", "updated_at": "2024-01-15T08:38:30.473904Z", "lead_time": 2.238, "prediction": {"id": 4695, "task": 97718, "score": null, "result": [{"type": "rectanglelabels", "score": 0.8264628648757935, "value": {"x": 7.033531188964844, "y": 3.3487396240234375, "width": 64.20580291748047, "height": 69.46102142333984, "rectanglelabels": ["L"]}, "to_name": "image", "from_name": "label"}], "cluster": null, "neighbors": null, "created_at": "2024-01-06T10:43:31.715372Z", "updated_at": "2024-01-06T10:43:31.715400Z", "created_ago": "1\u00a0week, 1\u00a0day", "mislabeling": 0.0, "model_version": "4"}, "result_count": 0, "parent_prediction": 4695, "parent_annotation": null}], "drafts": [], "predictions": [4695], "data": {"image": "repo://1f7b73bdedcba73296b429e0036c55fcc4df7a4b/data_first_draft/L2694.jpg"}, "meta": {}}