{"annotations": [{"completed_by": {"username": "massimiliano96", "first_name": "massimiliano96", "last_name": "", "avatar": "https://dagshub.com/avatars/16328"}, "result": [{"id": "hxR0mD4Q62", "type": "rectanglelabels", "score": 0.9735860228538513, "value": {"x": 26.137657165527344, "y": 31.546966552734375, "width": 43.27381134033203, "height": 56.65033721923828, "rotation": 0, "rectanglelabels": ["X"]}, "origin": "prediction", "to_name": "image", "from_name": "label", "image_rotation": 0, "original_width": 200, "original_height": 200}], "was_cancelled": false, "ground_truth": false, "created_at": "2024-04-10T15:55:55.873735Z", "updated_at": "2024-04-10T15:55:55.873738Z", "lead_time": 1.163, "prediction": {"id": 6298, "task": 99193, "score": null, "result": [{"type": "rectanglelabels", "score": 0.9735860228538513, "value": {"x": 26.137657165527344, "y": 31.546966552734375, "width": 43.27381134033203, "height": 56.65033721923828, "rectanglelabels": ["X"]}, "to_name": "image", "from_name": "label"}], "cluster": null, "neighbors": null, "created_at": "2024-01-06T11:07:40.546642Z", "updated_at": "2024-01-06T11:07:40.546677Z", "created_ago": "3\u00a0months", "mislabeling": 0.0, "model_version": "4"}, "result_count": 0, "parent_prediction": 6298, "parent_annotation": null}], "drafts": [], "predictions": [6298], "data": {"image": "repo://1f7b73bdedcba73296b429e0036c55fcc4df7a4b/data_first_draft/X895.jpg"}, "meta": {}}